dconnector/__init__.py
dconnector/mongodb_conn.py
dconnector-0.1.0.dist-info/METADATA
dconnector-0.1.0.dist-info/WHEEL
dconnector-0.1.0.dist-info/top_level.txt
dconnector-0.1.0.dist-info/RECORD
