Metadata-Version: 2.1
Name: dconnector
Version: 0.1.0
Summary: The dconnector Python package provides a streamlined interface for connecting to MongoDB databases using the MongoDBConnection class in Streamlit Projects. This class encapsulates common MongoDB operations, such as querying, inserting, updating, and deleting documents, and provides a convenient way to interact with MongoDB collections using pandas DataFrames.
Author: Ddhruv Arora
Author-email: <ddhruvarora2@gmail.com>
Provides: dconnector
Requires-Python: >=3.6
Requires-Dist: streamlit
Requires-Dist: pymongo
Requires-Dist: pandas
